dify_client/__init__.py
dify_client/_clientx.py
dify_client/errors.py
dify_client/models/__init__.py
dify_client/models/base.py
dify_client/models/chat.py
dify_client/models/completion.py
dify_client/models/feedback.py
dify_client/models/file.py
dify_client/models/stream.py
dify_client/models/workflow.py
dify_client/utils/__init__.py
dify_client/utils/_common.py
dify_client_python-1.0.1.dist-info/LICENSE
dify_client_python-1.0.1.dist-info/METADATA
dify_client_python-1.0.1.dist-info/WHEEL
dify_client_python-1.0.1.dist-info/top_level.txt
dify_client_python-1.0.1.dist-info/RECORD
