Metadata-Version: 2.1
Name: dify-client-python
Version: 1.0.1
Summary: A package for interacting with the Dify Service-API
Home-page: https://github.com/haoyuhu/dify-client-python
Author: haoyuhu
Author-email: im@huhaoyu.com
License: MIT
Keywords: dify nlp ai language-processing
Platform: UNKNOWN
Classifier: Programming Language :: Python :: 3
Classifier: License :: OSI Approved :: MIT License
Classifier: Operating System :: OS Independent
Requires-Python: >=3.7
Requires-Dist: httpx
Requires-Dist: httpx-sse
Requires-Dist: pydantic
Requires-Dist: StrEnum
